langchain_featherless_ai/__init__.py
langchain_featherless_ai/chat_models.py
langchain_featherless_ai/document_loaders.py
langchain_featherless_ai/embeddings.py
langchain_featherless_ai/py.typed
langchain_featherless_ai/retrievers.py
langchain_featherless_ai/toolkits.py
langchain_featherless_ai/tools.py
langchain_featherless_ai/vectorstores.py
langchain_featherless_ai-0.1.2.dist-info/LICENSE
langchain_featherless_ai-0.1.2.dist-info/METADATA
langchain_featherless_ai-0.1.2.dist-info/WHEEL
langchain_featherless_ai-0.1.2.dist-info/RECORD
