Metadata-Version: 2.3
Name: langchain-featherless-ai
Version: 0.1.2
Summary: An integration package connecting FeatherlessAi and LangChain
License: MIT
Requires-Python: >=3.9,<4.0
Classifier: License :: OSI Approved :: MIT License
Classifier: Programming Language :: Python :: 3
Classifier: Programming Language :: Python :: 3.9
Classifier: Programming Language :: Python :: 3.10
Classifier: Programming Language :: Python :: 3.11
Classifier: Programming Language :: Python :: 3.12
Classifier: Programming Language :: Python :: 3.13
Requires-Dist: langchain-core (>=0.3.15,<0.4.0)
Requires-Dist: langchain-openai (>=0.3.16,<0.4.0)
Project-URL: Repository, https://github.com/featherlessai/langchain-featherless-ai
Project-URL: Release Notes, https://github.com/langchain-ai/langchain/releases?q=tag%3A%22featherless-ai%3D%3D0%22&expanded=true
Project-URL: Source Code, https://github.com/langchain-ai/langchain/tree/master/libs/partners/featherless-ai
